markdown_katex/__init__.py
markdown_katex/__main__.py
markdown_katex/extension.py
markdown_katex/html.py
markdown_katex/wrapper.py
markdown_katex/bin/katex_v0.15.1_node10_x86_64-Darwin
markdown_katex/bin/katex_v0.15.1_node10_x86_64-Linux
markdown_katex/bin/katex_v0.15.1_node12_x86_64-Windows.exe
markdown_katex-202406.1035.dist-info/LICENSE
markdown_katex-202406.1035.dist-info/METADATA
markdown_katex-202406.1035.dist-info/WHEEL
markdown_katex-202406.1035.dist-info/entry_points.txt
markdown_katex-202406.1035.dist-info/top_level.txt
markdown_katex-202406.1035.dist-info/zip-safe
markdown_katex-202406.1035.dist-info/RECORD
