Metadata-Version: 2.1
Name: markdown-katex
Version: 202406.1035
Summary: katex extension for Python Markdown
Home-page: https://github.com/mbarkhau/markdown-katex
Author: Manuel Barkhau
Author-email: mbarkhau@gmail.com
License: MIT
Keywords: markdown katex extension
Classifier: Development Status :: 4 - Beta
Classifier: Environment :: Console
Classifier: Environment :: Other Environment
Classifier: Intended Audience :: Developers
Classifier: License :: OSI Approved :: MIT License
Classifier: Operating System :: Unix
Classifier: Operating System :: POSIX
Classifier: Operating System :: MacOS :: MacOS X
Classifier: Operating System :: Microsoft :: Windows
Classifier: Programming Language :: Python
Classifier: Programming Language :: Python :: 2.7
Classifier: Programming Language :: Python :: 3
Classifier: Programming Language :: Python :: Implementation :: CPython
Classifier: Programming Language :: Python :: Implementation :: PyPy
Classifier: Topic :: Software Development :: Libraries
Classifier: Topic :: Software Development :: Libraries :: Python Modules
Requires-Python: >=2.7
License-File: LICENSE
Requires-Dist: Markdown<3.3,>=3.0; python_version < "3.6"
Requires-Dist: Markdown>=3.0; python_version >= "3.6"
Requires-Dist: pathlib2; python_version < "3.4"
Requires-Dist: typing; python_version < "3.5"
Requires-Dist: setuptools
